enos_kubernetes/__init__.py
enos_kubernetes/build_conf.yml
enos_kubernetes/cli.py
enos_kubernetes/constants.py
enos_kubernetes/tasks.py
enos_kubernetes/ansible/post_install.yml
enos_kubernetes/ansible/site.yml
enos_kubernetes/ansible/roles/common/tasks/backup.yml
enos_kubernetes/ansible/roles/common/tasks/deploy.yml
enos_kubernetes/ansible/roles/common/tasks/destroy.yml
enos_kubernetes/ansible/roles/common/tasks/g5k.yml
enos_kubernetes/ansible/roles/common/tasks/main.yml
enos_kubernetes/ansible/roles/post_install/defaults/main.yml
enos_kubernetes/ansible/roles/post_install/files/dashboard/admin-serviceaccount.yaml
enos_kubernetes/ansible/roles/post_install/tasks/dashboard.yml
enos_kubernetes/ansible/roles/post_install/tasks/main.yml
enos_kubernetes/ansible/roles/post_install/tasks/monitoring.yml
enos_kubernetes-2.0.0.dist-info/LICENSE.txt
enos_kubernetes-2.0.0.dist-info/METADATA
enos_kubernetes-2.0.0.dist-info/WHEEL
enos_kubernetes-2.0.0.dist-info/entry_points.txt
enos_kubernetes-2.0.0.dist-info/top_level.txt
enos_kubernetes-2.0.0.dist-info/RECORD
